README.rst
setup.cfg
setup.py
parsewkt/__init__.py
parsewkt/parse.py
parsewkt/test_main.py
parsewkt/wkt.py
parsewkt.egg-info/PKG-INFO
parsewkt.egg-info/SOURCES.txt
parsewkt.egg-info/dependency_links.txt
parsewkt.egg-info/entry_points.txt
parsewkt.egg-info/not-zip-safe
parsewkt.egg-info/requires.txt
parsewkt.egg-info/top_level.txt