Metadata-Version: 1.0
Name: parsewkt
Version: 0.1dev
Summary: WKT Parser
Home-page: https://github.com/cleder/parsewkt
Author: Christian Ledermann
Author-email: christian.ledermann@gmail.com
License: LGPL
Keywords: WKT GIS Spatial
Platform: UNKNOWN
Classifier: Topic :: Scientific/Engineering :: GIS
Classifier: Programming Language :: Python
Classifier: Programming Language :: Python :: 2
Classifier: Programming Language :: Python :: 2.7
Classifier: Programming Language :: Python :: 3
Classifier: Programming Language :: Python :: 3.3
Classifier: Intended Audience :: Developers
Classifier: License :: OSI Approved :: GNU Library or Lesser General Public License (LGPL)
Classifier: Development Status :: 4 - Beta
Classifier: Operating System :: OS Independent
